{"0": ["334", "轟音", "08/01 01:38", 0, 0, 0, 4], "1": ["334", "轟音", "08/02 01:06", "0", "0", "0", "0"], "2": ["335", "轟音", "08/01 01:40", "0", "0", "0", "15"], "3": ["335", "轟音", "08/02 01:07", "0", "0", "0", "0"], "4": ["336", "轟音", "07/26 01:17", "0", "0", "0", "0"], "5": ["336", "轟音", "07/26 23:47", "0", "0", "0", "0"], "6": ["336", "轟音", "07/27 23:55", 0, 0, 0, 0], "7": ["336", "轟音", "07/29 00:32", "0", "", "", "0"], "8": ["336", "轟音", "07/30 00:41", "0", "0", "0", "0"], "9": ["336", "轟音", "07/31 01:33", "0", "0", "0", "0"], "10": ["336", "轟音", "08/01 01:41", "0", "0", "0", "0"], "11": ["336", "轟音", "08/02 01:08", "0", "0", "28", "0"], "12": ["337", "轟音", "07/26 01:18", 0, 0, 12, 0], "13": ["337", "轟音", "07/26 23:49", "0", "0", "0", "12"], "14": ["337", "轟音", "07/28 00:14", "0", "0", "47", "0"], "15": ["337", "轟音", "07/29 00:33", "0", "0", "0", "47"], "16": ["337", "轟音", "07/30 00:42", "0", "", "", "0"], "17": ["337", "轟音", "07/31 01:34", "0", "0", "2", "0"], "18": ["337", "轟音", "08/01 01:42", "0", "0", "0", "2"], "19": ["337", "轟音", "08/02 01:09", "0", "0", "0", "0"], "20": ["453", "決戦", "07/26 23:50", 0, 0, 16, 11], "21": ["453", "決戦", "07/28 00:15", "0", "0", "0", "16"], "22": ["453", "決戦", "07/29 00:37", "0", "0", "0", "0"], "23": ["453", "決戦", "07/30 00:46", "0", "0", "0", "0"], "24": ["453", "決戦", "07/31 01:37", "0", "0", "0", "0"], "25": ["453", "決戦", "08/01 01:47", 0, 0, 53, 0], "26": ["453", "決戦", "08/02 01:17", 0, 0, 105, 53], "27": ["454", "決戦", "07/26 23:51", "0", "0", "85", "26"], "28": ["454", "決戦", "07/28 00:17", "0", "0", "0", "85"], "29": ["454", "決戦", "07/29 00:38", "0", "0", "1", "0"], "30": ["454", "決戦", "07/30 00:48", "0", "0", "0", "1"], "31": ["454", "決戦", "07/31 01:38", "0", "0", "0", "0"], "32": ["454", "決戦", "08/01 01:48", "0", "0", "4", "0"], "33": ["454", "決戦", "08/02 01:18", "0", "0", "0", "4"], "34": ["46", "タロウ", "08/02 00:41", "0", "0", "140", "0"], "35": ["601", "999", "08/02 01:29", "0", "0", "29", "4"]}